odoo10_addon_account_fiscal_position_rule_stock-10.0.1.0.0.99.dev19-nspkg.pth
odoo/addons/account_fiscal_position_rule_stock/README.rst
odoo/addons/account_fiscal_position_rule_stock/__init__.py
odoo/addons/account_fiscal_position_rule_stock/__manifest__.py
odoo/addons/account_fiscal_position_rule_stock/demo/account_fiscal_position_rule_stock_demo.xml
odoo/addons/account_fiscal_position_rule_stock/i18n/account_fiscal_position_rule_stock.pot
odoo/addons/account_fiscal_position_rule_stock/i18n/en_US.po
odoo/addons/account_fiscal_position_rule_stock/i18n/pt_BR.po
odoo/addons/account_fiscal_position_rule_stock/models/__init__.py
odoo/addons/account_fiscal_position_rule_stock/models/stock_picking.py
odoo/addons/account_fiscal_position_rule_stock/security/ir.model.access.csv
odoo/addons/account_fiscal_position_rule_stock/static/description/icon.png
odoo/addons/account_fiscal_position_rule_stock/tests/__init__.py
odoo/addons/account_fiscal_position_rule_stock/tests/test_account_fiscal_position_rule_stock.py
odoo/addons/account_fiscal_position_rule_stock/views/stock_picking.xml
odoo/addons/account_fiscal_position_rule_stock/wizards/__init__.py
odoo/addons/account_fiscal_position_rule_stock/wizards/stock_invoice_onshipping.py
odoo10_addon_account_fiscal_position_rule_stock-10.0.1.0.0.99.dev19.dist-info/METADATA
odoo10_addon_account_fiscal_position_rule_stock-10.0.1.0.0.99.dev19.dist-info/WHEEL
odoo10_addon_account_fiscal_position_rule_stock-10.0.1.0.0.99.dev19.dist-info/namespace_packages.txt
odoo10_addon_account_fiscal_position_rule_stock-10.0.1.0.0.99.dev19.dist-info/top_level.txt
odoo10_addon_account_fiscal_position_rule_stock-10.0.1.0.0.99.dev19.dist-info/RECORD
